flet_pdfviewer/__init__.py
flet_pdfviewer/flet_pdfviewer.py
flutter/flet_pdfviewer/CHANGELOG.md
flutter/flet_pdfviewer/LICENSE
flutter/flet_pdfviewer/README.md
flutter/flet_pdfviewer/pubspec.lock
flutter/flet_pdfviewer/pubspec.yaml
flutter/flet_pdfviewer/lib/flet_pdfviewer.dart
flutter/flet_pdfviewer/lib/src/create_control.dart
flutter/flet_pdfviewer/lib/src/flet_pdfviewer.dart
flet_pdfviewer-0.1.0.dist-info/METADATA
flet_pdfviewer-0.1.0.dist-info/WHEEL
flet_pdfviewer-0.1.0.dist-info/top_level.txt
flet_pdfviewer-0.1.0.dist-info/RECORD
