Metadata-Version: 2.2
Name: flet-pdfviewer
Version: 0.1.0
Summary: FletPdfviewer control for Flet
Author-email: Edoardo Balducci <edoardoba2004@gmail.com>
Project-URL: Homepage, https://mydomain.dev
Project-URL: Documentation, https://github.com/MyGithubAccount/flet-pdfviewer
Project-URL: Repository, https://github.com/MyGithubAccount/flet-pdfviewer
Project-URL: Issues, https://github.com/MyGithubAccount/flet-pdfviewer/issues
Requires-Python: >=3.9
Requires-Dist: flet>=0.27.6
